LICENSE
README.rst
flask_heroku_runner.py
requirements.txt
setup.cfg
setup.py
tests.py
Flask_Heroku_Runner.egg-info/PKG-INFO
Flask_Heroku_Runner.egg-info/SOURCES.txt
Flask_Heroku_Runner.egg-info/dependency_links.txt
Flask_Heroku_Runner.egg-info/not-zip-safe
Flask_Heroku_Runner.egg-info/requires.txt
Flask_Heroku_Runner.egg-info/top_level.txt
docs/conf.py
docs/index.rst
docs/_themes/LICENSE
docs/_themes/README
docs/_themes/flask_theme_support.py
docs/_themes/flask_small/layout.html
docs/_themes/flask_small/theme.conf
docs/_themes/flask_small/static/flasky.css_t
docs/_themes/flask_small/static/fork_me_bitbucket.png