Metadata-Version: 1.0
Name: Flask-Heroku-Runner
Version: 1
Summary: Minimalist Heroku bootstrap for Flask
Home-page: http://bitbucket.org/daveshawley/flask-heroku-runner/
Author: Dave Shawley
Author-email: daveshawley@gmail.com
License: BSD
Platform: any
Classifier: Environment :: Web Environment
Classifier: Intended Audience :: Developers
Classifier: License :: OSI Approved :: BSD License
Classifier: Operating System :: OS Independent
Classifier: Programming Language :: Python
